<?xml version="1.0" encoding="UTF-8"?>
<!DOCTYPE mapper PUBLIC "-//mybatis.org//DTD Mapper 3.0//EN" "http://mybatis.org/dtd/mybatis-3-mapper.dtd">
<mapper namespace="com.zxb.ownmallmapper.mapper.UmsAdminRoleMapper">
  <resultMap id="BaseResultMap" type="com.zxb.ownmallmapper.pojo.UmsAdminRole">
    <!--
      WARNING - @mbggenerated
      This element is automatically generated by MyBatis Generator, do not modify.
    -->
    <id column="admin_id" jdbcType="VARCHAR" property="adminId" />
    <id column="role_id" jdbcType="VARCHAR" property="roleId" />
  </resultMap>
  <delete id="deleteByPrimaryKey" parameterType="map">
    <!--
      WARNING - @mbggenerated
      This element is automatically generated by MyBatis Generator, do not modify.
    -->
    delete from ums_admin_role
    where admin_id = #{adminId,jdbcType=VARCHAR}
      and role_id = #{roleId,jdbcType=VARCHAR}
  </delete>
  <insert id="insert" parameterType="com.zxb.ownmallmapper.pojo.UmsAdminRole">
    <!--
      WARNING - @mbggenerated
      This element is automatically generated by MyBatis Generator, do not modify.
    -->
    insert into ums_admin_role (admin_id, role_id)
    values (#{adminId,jdbcType=VARCHAR}, #{roleId,jdbcType=VARCHAR})
  </insert>
  <select id="selectAll" resultMap="BaseResultMap">
    <!--
      WARNING - @mbggenerated
      This element is automatically generated by MyBatis Generator, do not modify.
    -->
    select admin_id, role_id
    from ums_admin_role
  </select>
</mapper>